src/register_3bit.v
module register_3bit(
    input clk,
    input reset,
    input [2:0] d,
    output reg [2:0] q
);

always @(posedge clk or posedge reset) begin
    if (reset)
        q <= 3'b000;
    else
        q <= d;
end

endmodule

src/full-adder.v
module full_adder(
    input a, b, cin,
    output sum, cout
);

assign sum = a ^ b ^ cin;
assign cout = (a & b) | (cin & (a ^ b));

endmodule

src/adder_3bit.v
module adder_3bit(
    input [2:0] a,
    input [2:0] b,
    input cin,
    output [2:0] sum,
    output cout
);

wire c1, c2;

full_adder fa0(a[0], b[0], cin, sum[0], c1);
full_adder fa1(a[1], b[1], c1, sum[1], c2);
full_adder fa2(a[2], b[2], c2, sum[2], cout);

endmodule

src/system.v
module system(
    input clk,
    input reset,
    input up_down, // 0 = soma | 1 = subtrai
    output [2:0] q
);

wire [2:0] current;
wire [2:0] next;
wire [2:0] operand;
wire cout;

// Define +1 ou -1 (complemento de 2)
assign operand = (up_down == 0) ? 3'b001 : 3'b111;

// Somador
adder_3bit adder(
    .a(current),
    .b(operand),
    .cin(1'b0),
    .sum(next),
    .cout(cout)
);

// Registrador
register_3bit reg1(
    .clk(clk),
    .reset(reset),
    .d(next),
    .q(current)
);

assign q = current;

endmodule

sim/system_tb.v
`timescale 1ns/1ps

module system_tb;

reg clk;
reg reset;
reg up_down;
wire [2:0] q;

// Instancia o sistema
system uut (
    .clk(clk),
    .reset(reset),
    .up_down(up_down),
    .q(q)
);

// Clock
always #5 clk = ~clk;

initial begin
    $dumpfile("wave/output.vcd");
    $dumpvars(0, system_tb);

    clk = 0;
    reset = 1;
    up_down = 0;

    #10 reset = 0;

    // Incrementa
    #60;

    // Decrementa
    up_down = 1;
    #60;

    // Incrementa de novo
    up_down = 0;
    #40;

    $finish;
end

endmodule

wave/output.vcd
$date
	Sat Apr 25 23:28:49 2026
$end
$version
	Icarus Verilog
$end
$timescale
	1ps
$end
$scope module system_tb $end
$var wire 3 ! q [2:0] $end
$var reg 1 " clk $end
$var reg 1 # reset $end
$var reg 1 $ up_down $end
$scope module uut $end
$var wire 1 " clk $end
$var wire 3 % q [2:0] $end
$var wire 1 # reset $end
$var wire 1 $ up_down $end
$var wire 3 & operand [2:0] $end
$var wire 3 ' next [2:0] $end
$var wire 3 ( current [2:0] $end
$var wire 1 ) cout $end
$scope module adder $end
$var wire 3 * b [2:0] $end
$var wire 1 + cin $end
$var wire 3 , sum [2:0] $end
$var wire 1 ) cout $end
$var wire 1 - c2 $end
$var wire 1 . c1 $end
$var wire 3 / a [2:0] $end
$scope module fa0 $end
$var wire 1 0 a $end
$var wire 1 1 b $end
$var wire 1 + cin $end
$var wire 1 . cout $end
$var wire 1 2 sum $end
$upscope $end
$scope module fa1 $end
$var wire 1 3 a $end
$var wire 1 4 b $end
$var wire 1 . cin $end
$var wire 1 - cout $end
$var wire 1 5 sum $end
$upscope $end
$scope module fa2 $end
$var wire 1 6 a $end
$var wire 1 7 b $end
$var wire 1 - cin $end
$var wire 1 ) cout $end
$var wire 1 8 sum $end
$upscope $end
$upscope $end
$scope module reg1 $end
$var wire 1 " clk $end
$var wire 3 9 d [2:0] $end
$var wire 1 # reset $end
$var reg 3 : q [2:0] $end
$upscope $end
$upscope $end
$upscope $end
$enddefinitions $end
$comment Show the parameter values. $end
$dumpall
$end
#0
$dumpvars
b0 :
b1 9
08
07
06
05
04
03
12
11
00
b0 /
0.
0-
b1 ,
0+
b1 *
0)
b0 (
b1 '
b1 &
b0 %
0$
1#
0"
b0 !
$end
#5000
1"
#10000
0"
0#
#15000
15
b10 '
b10 ,
b10 9
02
1.
10
b1 !
b1 %
b1 (
b1 /
b1 :
1"
#20000
0"
#25000
b11 '
b11 ,
b11 9
12
0.
13
00
b10 !
b10 %
b10 (
b10 /
b10 :
1"
#30000
0"
#35000
18
1-
05
b100 '
b100 ,
b100 9
02
1.
10
b11 !
b11 %
b11 (
b11 /
b11 :
1"
#40000
0"
#45000
0)
0-
18
b101 '
b101 ,
b101 9
12
0.
16
03
00
b100 !
b100 %
b100 (
b100 /
b100 :
1"
#50000
0"
#55000
15
b110 '
b110 ,
b110 9
02
1.
10
b101 !
b101 %
b101 (
b101 /
b101 :
1"
#60000
0"
#65000
b111 '
b111 ,
b111 9
12
0.
13
00
b110 !
b110 %
b110 (
b110 /
b110 :
1"
#70000
05
1-
b101 '
b101 ,
b101 9
18
1)
14
17
b111 &
b111 *
0"
1$
#75000
b100 '
b100 ,
b100 9
02
1.
03
10
b101 !
b101 %
b101 (
b101 /
b101 :
1"
#80000
0"
#85000
08
0-
15
b11 '
b11 ,
b11 9
12
0.
00
b100 !
b100 %
b100 (
b100 /
b100 :
1"
#90000
0"
#95000
1-
b10 '
b10 ,
b10 9
02
1.
06
13
10
b11 !
b11 %
b11 (
b11 /
b11 :
1"
#100000
0"
#105000
05
b1 '
b1 ,
b1 9
12
0.
00
b10 !
b10 %
b10 (
b10 /
b10 :
1"
#110000
0"
#115000
b0 '
b0 ,
b0 9
02
1.
03
10
b1 !
b1 %
b1 (
b1 /
b1 :
1"
#120000
0"
#125000
0)
18
0-
15
b111 '
b111 ,
b111 9
12
0.
00
b0 !
b0 %
b0 (
b0 /
b0 :
1"
#130000
05
b1 '
b1 ,
b1 9
08
04
07
b1 &
b1 *
0"
0$
#135000
15
b10 '
b10 ,
b10 9
02
1.
10
b1 !
b1 %
b1 (
b1 /
b1 :
1"
#140000
0"
#145000
b11 '
b11 ,
b11 9
12
0.
13
00
b10 !
b10 %
b10 (
b10 /
b10 :
1"
#150000
0"
#155000
18
1-
05
b100 '
b100 ,
b100 9
02
1.
10
b11 !
b11 %
b11 (
b11 /
b11 :
1"
#160000
0"
#165000
0)
0-
18
b101 '
b101 ,
b101 9
12
0.
16
03
00
b100 !
b100 %
b100 (
b100 /
b100 :
1"
